aigents/__init__.py
aigents/base.py
aigents/constants.py
aigents/context/__init__.py
aigents/context/base.py
aigents/context/core.py
aigents/context/errors.py
aigents/context/nlp/__init__.py
aigents/context/nlp/base.py
aigents/context/nlp/constants.py
aigents/context/nlp/errors.py
aigents/context/nlp/processors.py
aigents/context/nlp/utils.py
aigents/context/utils.py
aigents/core.py
aigents/data.py
aigents/errors.py
aigents/prompts.py
aigents/settings.py
aigents/utils.py
aigents-0.13.0.dist-info/LICENSE
aigents-0.13.0.dist-info/METADATA
aigents-0.13.0.dist-info/WHEEL
aigents-0.13.0.dist-info/RECORD
