Metadata-Version: 2.1
Name: aigents
Version: 0.13.0
Summary: Adapters for Large Language Models and Generative Pre-trained Transformers APIs
Home-page: https://github.com/bessavagner/aigents.git
License: GPL-3.0-only
Author: Vagner Bessa
Author-email: bessavagner@gmail.com
Requires-Python: >=3.10,<4.0
Classifier: Development Status :: 4 - Beta
Classifier: Intended Audience :: Developers
Classifier: License :: OSI Approved :: GNU General Public License v3 (GPLv3)
Classifier: Programming Language :: Python :: 3
Classifier: Programming Language :: Python :: 3.10
Classifier: Programming Language :: Python :: 3.11
Classifier: Programming Language :: Python :: 3.12
Classifier: Topic :: Software Development :: Libraries :: Python Modules
Requires-Dist: g4f[all] (>=0.2.4.1,<0.3.0.0)
Requires-Dist: google-generativeai (>=0.5.4,<0.6.0)
Requires-Dist: nltk (>=3.8.1,<4.0.0)
Requires-Dist: openai (>=1.12.0,<2.0.0)
Requires-Dist: pandas (>=2.2.2,<3.0.0)
Requires-Dist: pillow (>=10.2.0,<11.0.0)
Requires-Dist: pypdf (>=5.0.0,<6.0.0)
Requires-Dist: python-dotenv (>=1.0.1,<2.0.0)
Requires-Dist: scipy (>=1.13.0,<2.0.0)
Requires-Dist: spacy (>=3.7.4,<4.0.0)
Requires-Dist: tiktoken (>=0.6.0,<0.7.0)
Requires-Dist: tomlkit (>=0.12.4,<0.13.0)
Project-URL: Repository, https://github.com/bessavagner/aigents.git
